send2trash-stubs/METADATA.toml
send2trash-stubs/__init__.pyi
send2trash-stubs/__main__.pyi
send2trash-stubs/exceptions.pyi
send2trash-stubs/py.typed
send2trash-stubs/util.pyi
types_send2trash-2.1.0.20260117.dist-info/licenses/LICENSE
types_send2trash-2.1.0.20260117.dist-info/METADATA
types_send2trash-2.1.0.20260117.dist-info/WHEEL
types_send2trash-2.1.0.20260117.dist-info/top_level.txt
types_send2trash-2.1.0.20260117.dist-info/RECORD
